schwarz/log_utils/__init__.py
schwarz/log_utils/callback_logger.py
schwarz/log_utils/forwarding_logger.py
schwarz/log_utils/log_proxy.py
schwarz/log_utils/testutils.py
schwarzlog-0.7.0.dist-info/LICENSE.txt
schwarzlog-0.7.0.dist-info/METADATA
schwarzlog-0.7.0.dist-info/WHEEL
schwarzlog-0.7.0.dist-info/top_level.txt
schwarzlog-0.7.0.dist-info/RECORD
