Metadata-Version: 2.1
Name: schwarzlog
Version: 0.7.0
Summary: UNKNOWN
Home-page: https://github.com/FelixSchwarz/log_utils
Author: Felix Schwarz
Author-email: felix.schwarz@oss.schwarz.eu
License: MIT
Platform: UNKNOWN
Requires-Python: >=3.6
License-File: LICENSE.txt
Provides-Extra: testing
Requires-Dist: pytest ; extra == 'testing'
Requires-Dist: testfixtures ; extra == 'testing'
